fonticon_fa5/__init__.py
fonticon_fa5/_iconfont.py
fonticon_fa5/fa5b.py
fonticon_fa5/fa5r.py
fonticon_fa5/fa5s.py
fonticon_fa5/_tests/test_font.py
fonticon_fa5/fonts/Font Awesome 5 Brands-Regular-400.otf
fonticon_fa5/fonts/Font Awesome 5 Free-Regular-400.otf
fonticon_fa5/fonts/Font Awesome 5 Free-Solid-900.otf
fonticon_fa5/fonts/LICENSE.txt
fonticon_fontawesome5-5.15.4.dist-info/LICENSE
fonticon_fontawesome5-5.15.4.dist-info/METADATA
fonticon_fontawesome5-5.15.4.dist-info/WHEEL
fonticon_fontawesome5-5.15.4.dist-info/entry_points.txt
fonticon_fontawesome5-5.15.4.dist-info/top_level.txt
fonticon_fontawesome5-5.15.4.dist-info/RECORD
