Metadata-Version: 2.1
Name: fonticon-fontawesome5
Version: 5.15.4
Summary: FontAwesome 5 extension for superqt font icons
Home-page: https://github.com/tlambert03/fonticon-fontawesome5
Author: Talley Lambert
Author-email: talley.lambert@gmail.com
License: MIT license
Project-URL: Source Code, https://github.com/tlambert03/fonticon-fontawesome5
Platform: UNKNOWN
Classifier: Development Status :: 4 - Beta
Classifier: License :: OSI Approved :: MIT License
Classifier: Natural Language :: English
Classifier: Programming Language :: Python :: 3
Classifier: Programming Language :: Python :: 3.6
Classifier: Programming Language :: Python :: 3.7
Classifier: Programming Language :: Python :: 3.8
Classifier: Programming Language :: Python :: 3.9
Requires-Python: >=3.6
License-File: LICENSE
Provides-Extra: testing
Requires-Dist: pytest ; extra == 'testing'
Requires-Dist: superqt ; extra == 'testing'
Requires-Dist: pytest-qt ; extra == 'testing'
